DESCRIPTION.rst
MANIFEST.in
setup.cfg
setup.py
hubot_hangups.egg-info/PKG-INFO
hubot_hangups.egg-info/SOURCES.txt
hubot_hangups.egg-info/dependency_links.txt
hubot_hangups.egg-info/requires.txt
hubot_hangups.egg-info/top_level.txt
sample/__init__.py
sample/package_data.dat