Metadata-Version: 1.1
Name: hubot-hangups
Version: 1.0.0
Summary: A hubot adapter for Google Hangouts
Home-page: https://github.com/groupby/hubot-hangups
Author: Eric Hacke
Author-email: eric.hacke@groupbyinc.com
License: MIT
Keywords: hubot adapter google hangouts hangups
Platform: UNKNOWN
Classifier: Development Status :: 4 - Beta
Classifier: Intended Audience :: Developers
Classifier: Topic :: Communications :: Chat
Classifier: License :: OSI Approved :: MIT License
Classifier: Programming Language :: Python :: 3.3
Classifier: Programming Language :: Python :: 3.4
